biblescrapeway/__init__.py
biblescrapeway/cache.py
biblescrapeway/cleaner.py
biblescrapeway/cli.py
biblescrapeway/constants.py
biblescrapeway/errors.py
biblescrapeway/query.py
biblescrapeway/reference.py
biblescrapeway/scraper.py
biblescrapeway/version.py
biblescrapeway-0.1.7.dist-info/LICENSE
biblescrapeway-0.1.7.dist-info/METADATA
biblescrapeway-0.1.7.dist-info/WHEEL
biblescrapeway-0.1.7.dist-info/entry_points.txt
biblescrapeway-0.1.7.dist-info/top_level.txt
biblescrapeway-0.1.7.dist-info/RECORD
