Metadata-Version: 2.1
Name: biblescrapeway
Version: 0.1.7
Summary: A tool for scraping bible verses from the web
Home-page: https://github.com/jonathanvanschenck/biblescrapeway
Author: Jonathan D B Van Schenck
Author-email: vanschej@oregonstate.edu
License: UNKNOWN
Platform: UNKNOWN
Classifier: Programming Language :: Python :: 3
Classifier: License :: OSI Approved :: MIT License
Classifier: Operating System :: OS Independent
Requires-Dist: Click
Requires-Dist: beautifulsoup4
Requires-Dist: requests
